animate_transit/__init__.py
animate_transit/main.py
animate_transit-1.0.dist-info/METADATA
animate_transit-1.0.dist-info/WHEEL
animate_transit-1.0.dist-info/top_level.txt
animate_transit-1.0.dist-info/RECORD
